git_notes_db/__init__.py
git_notes_db/__main__.py
git_notes_db/cli.py
git_notes_db/commands.py
git_notes_db/git.py
git_notes_db/helpers.py
git_notes_db/jq.py
git_notes_db/dev/__init__.py
git_notes_db/dev/commit.py
git_notes_db/dev/commit_helpers.py
git_notes_db/dev/cz_pre_bump.py
git_notes_db/dev/describe.py
git_notes_db-0.1.31.dist-info/licenses/LICENSE
git_notes_db-0.1.31.dist-info/METADATA
git_notes_db-0.1.31.dist-info/WHEEL
git_notes_db-0.1.31.dist-info/entry_points.txt
git_notes_db-0.1.31.dist-info/top_level.txt
git_notes_db-0.1.31.dist-info/RECORD
