Metadata-Version: 2.4
Name: git-notes-db
Version: 0.1.31
Summary: Store and access structured data in git-notes
Author-email: Chris Scutcher <chris@scutcher.uk>
License: This is free and unencumbered software released into the public domain.
Project-URL: Homepage, https://gitlab.com/cscutcher-public/git-notes-db
Project-URL: Repository, https://gitlab.com/cscutcher-public/git-notes-db.git
Project-URL: Homepage (Mirror), https://github.com/cscutcher/git-notes-db
Project-URL: Repository (Mirror), https://github.com/cscutcher/git-notes-db.git
Keywords: git,notes,cli,json,jq
Classifier: Development Status :: 4 - Beta
Classifier: License :: Public Domain
Classifier: Programming Language :: Python :: 3
Classifier: Programming Language :: Python :: 3.13
Classifier: Topic :: Software Development :: Version Control
Requires-Python: >=3.13
License-File: LICENSE
Requires-Dist: attrs>=25.3.0
Requires-Dist: gitpython>=3.1.44
Requires-Dist: jq>=1.9.1
Requires-Dist: more-itertools>=10.7.0
Requires-Dist: pydantic>=2.11.7
Requires-Dist: rich>=14.0.0
Dynamic: license-file
